README.md
__init__.py
setup.py
dist/post_processing_pupil-0.1.0.tar.gz
dist/post_processing_pupil-0.1.1.tar.gz
dist/post_processing_pupil-0.1.2.tar.gz
dist/post_processing_pupil-0.1.3.tar.gz
dist/post_processing_pupil-0.1.4.tar.gz
post_processing_pupil/__init__.py
post_processing_pupil/post_processing_pupil.py
post_processing_pupil.egg-info/PKG-INFO
post_processing_pupil.egg-info/SOURCES.txt
post_processing_pupil.egg-info/dependency_links.txt
post_processing_pupil.egg-info/requires.txt
post_processing_pupil.egg-info/top_level.txt