Metadata-Version: 2.1
Name: post-processing-pupil
Version: 0.1.5
Summary: Python package to calculte output fixation points produced by the pupil-core eye tracker
Home-page: https://github.com/LostInZoom/post_processing_ET
Author: Laura Wenclik
Author-email: laura.wenclik@ign.fr
License: GPLv3
Keywords: pupil core,eye tracker
Platform: Linux
Platform: Mac OSX
Platform: Windows
Platform: Unix
Classifier: Development Status :: 1 - Planning
Classifier: Intended Audience :: Science/Research
Classifier: Programming Language :: Python :: 3.8
Classifier: Programming Language :: Python :: 3.9
Classifier: Programming Language :: Python :: 3.10
Classifier: Programming Language :: Python :: 3.11
Classifier: Programming Language :: Python :: 3 :: Only
Requires-Python: >=3.8
